sha512_crypt-0.1.1.dist-info/METADATA
sha512_crypt-0.1.1.dist-info/WHEEL
sha512_crypt/__init__.py
sha512_crypt/__init__.pyi
sha512_crypt/py.typed
sha512_crypt/sha512_crypt.abi3.so
sha512_crypt-0.1.1.dist-info/RECORD
