Metadata-Version: 2.1
Name: sha512-crypt
Version: 0.1.1
Summary: Python binding to Rust sha-crypt password hashing crate
License: MIT
Project-URL: Source Code, https://github.com/messense/sha512-crypt
